bitcoin_nostr_chat/__init__.py
bitcoin_nostr_chat/async_dm_connection.py
bitcoin_nostr_chat/async_thread.py
bitcoin_nostr_chat/base_dm.py
bitcoin_nostr_chat/bitcoin_dm.py
bitcoin_nostr_chat/chat.py
bitcoin_nostr_chat/default_relays.py
bitcoin_nostr_chat/dialogs.py
bitcoin_nostr_chat/dm_connection.py
bitcoin_nostr_chat/group_chat.py
bitcoin_nostr_chat/html.py
bitcoin_nostr_chat/label_connector.py
bitcoin_nostr_chat/nostr_sync.py
bitcoin_nostr_chat/notification_handler.py
bitcoin_nostr_chat/protocol_dm.py
bitcoin_nostr_chat/relay_list.py
bitcoin_nostr_chat/signals_min.py
bitcoin_nostr_chat/ui/__init__.py
bitcoin_nostr_chat/ui/bitcoin_dm_chat_gui.py
bitcoin_nostr_chat/ui/chat_component.py
bitcoin_nostr_chat/ui/chat_gui.py
bitcoin_nostr_chat/ui/device_manager.py
bitcoin_nostr_chat/ui/icons/clip.svg
bitcoin_nostr_chat/ui/icons/clip_darkmode.svg
bitcoin_nostr_chat/ui/icons/preferences.png
bitcoin_nostr_chat/ui/ui.py
bitcoin_nostr_chat/ui/util.py
bitcoin_nostr_chat/utils.py
bitcoin_nostr_chat-0.6.7.dist-info/LICENSE
bitcoin_nostr_chat-0.6.7.dist-info/METADATA
bitcoin_nostr_chat-0.6.7.dist-info/WHEEL
bitcoin_nostr_chat-0.6.7.dist-info/RECORD
