Metadata-Version: 2.1
Name: bitcoin-nostr-chat
Version: 0.6.7
Summary: A Nostr Chat with participant discovery
Home-page: https://github.com/andreasgriffin/bitcoin-nostr-chat
License: GPL-3.0
Author: andreasgriffin
Author-email: andreasgriffin@proton.me
Requires-Python: >=3.9,<3.13
Classifier: License :: OSI Approved :: GNU General Public License v3 (GPLv3)
Classifier: Programming Language :: Python :: 3
Classifier: Programming Language :: Python :: 3.9
Classifier: Programming Language :: Python :: 3.10
Classifier: Programming Language :: Python :: 3.11
Classifier: Programming Language :: Python :: 3.12
Requires-Dist: bitcoin-qr-tools (>=1.0.0,<2.0.0)
Requires-Dist: cbor2 (>=5.6.3,<6.0.0)
Requires-Dist: nostr-sdk (>=0.38.0,<0.39.0)
Requires-Dist: pyqt6 (>=6.6.1,<7.0.0)
Requires-Dist: requests (>=2.31.0,<3.0.0)
